packarch.py
PY_packArch-1.9.3.post1.dist-info/LICENSE
PY_packArch-1.9.3.post1.dist-info/METADATA
PY_packArch-1.9.3.post1.dist-info/WHEEL
PY_packArch-1.9.3.post1.dist-info/top_level.txt
PY_packArch-1.9.3.post1.dist-info/RECORD
