Metadata-Version: 2.1
Name: PY-packArch
Version: 1.9.3.post1
Summary: Small library to manage pacman package manager and install packages from AUR
Home-page: https://github.com/Tom5521/PY-PackArch
Author: Tom5521
Author-email: mismarttv321@gmail.com
License: GPL-3.0
Project-URL: Bug Tracker, https://github.com/Tom5521/PY-PackArch/issues
Project-URL: Documentation, https://github.com/Tom5521/PY-PackArch/blob/master/README.md
Project-URL: Download-url, https://github.com/Tom5521/PY-PackArch/archive/refs/heads/master.zip
Keywords: pacman,arch linux,linux,AUR
Classifier: License :: OSI Approved :: GNU General Public License v3 or later (GPLv3+)
Classifier: Operating System :: Unix
Classifier: Topic :: System :: Software Distribution
Classifier: Environment :: Console
Requires-Python: >=3.10
License-File: LICENSE
Requires-Dist: Tom-Toolbox
